pywfd/__init__.py
pywfd/chord.py
pywfd/const.py
pywfd/io.py
pywfd/label.py
pywfd/rhythm.py
pywfd/wfd.py
pywfd-1.3.2.dist-info/LICENSE
pywfd-1.3.2.dist-info/METADATA
pywfd-1.3.2.dist-info/WHEEL
pywfd-1.3.2.dist-info/top_level.txt
pywfd-1.3.2.dist-info/RECORD
