Metadata-Version: 2.1
Name: pywfd
Version: 1.3.2
Summary: A library to handle wfd files in python.
Home-page: https://github.com/anime-song/wfdload
Author: anime-song
Author-email: UNKNOWN
License: MIT
Platform: UNKNOWN
Requires-Dist: numpy
Requires-Dist: dlchord
